merkleshare/__init__.py
merkleshare/_version.py
merkleshare/merkleshare.py
merkleshare/webui/__init__.py
merkleshare/webui/webui.py
merkleshare/webui/output/index.html
merkleshare-0.4.4.dist-info/AUTHORS.rst
merkleshare-0.4.4.dist-info/LICENSE
merkleshare-0.4.4.dist-info/METADATA
merkleshare-0.4.4.dist-info/WHEEL
merkleshare-0.4.4.dist-info/entry_points.txt
merkleshare-0.4.4.dist-info/top_level.txt
merkleshare-0.4.4.dist-info/RECORD
