Metadata-Version: 2.1
Name: merkleshare
Version: 0.4.4
Summary: A no-brainer pastebin on IPFS - think distributed http://sprunge.us
Home-page: https://github.com/drozdziak1/merkleshare
Author: Stanislaw Drozd
Author-email: drozdziak1@gmail.com
License: MIT
Platform: UNKNOWN
Classifier: Development Status :: 2 - Pre-Alpha
Classifier: Intended Audience :: Developers
Classifier: License :: OSI Approved :: MIT License
Classifier: Natural Language :: English
Classifier: Programming Language :: Python :: 3
Classifier: Programming Language :: Python :: 3.4
Classifier: Programming Language :: Python :: 3.5
Classifier: Programming Language :: Python :: 3.6
Requires-Dist: base58
Requires-Dist: cryptography
Requires-Dist: ipfsapi
Requires-Dist: jinja2
Requires-Dist: morphys
